{
  "info": {
    "name": "CiblOrgaSport - Unified Tests",
    "_postman_id": "ciblorgasport-unified-001",
    "description": "Collection consolidée : auth, participants, event, incident, billetterie, abonnement, monolith. Use this single collection for all tests.",
    "schema": "https://schema.getpostman.com/json/collection/v2.1.0/collection.json"
  },
  "variable": [
    { "key": "api_base", "value": "http://localhost:3000" },
    { "key": "auth_base", "value": "http://localhost:8080" },
    { "key": "incident_base", "value": "http://localhost:8083" },
    { "key": "event_base", "value": "http://localhost:8084" },
    { "key": "billetterie_base", "value": "http://localhost:8081" },
    { "key": "abonnement_base", "value": "http://localhost:8082" },
    { "key": "participants_base", "value": "http://localhost:8087" },
    { "key": "token", "value": "" },
    { "key": "jwt", "value": "Bearer {{token}}" },
    { "key": "athlete_id", "value": "2" },
    { "key": "incident_id", "value": "" },
    { "key": "event_id", "value": "" },
    { "key": "competition_id", "value": "" },
    { "key": "ticket_id", "value": "" },
    { "key": "epreuve_id", "value": "" },
    { "key": "epreuve_participants_count", "value": "" },
    { "key": "lieu_id", "value": "" }
  ],
  "item": [
    {
      "name": "auth-service",
      "item": [
        {
          "name": "Register (commissaire)",
          "request": {
            "method": "POST",
            "header": [{ "key": "Content-Type", "value": "application/json" }],
            "body": { "mode": "raw", "raw": "{ \"username\": \"commissaire1\", \"email\": \"comm@example.com\", \"password\": \"commiss123\", \"role\": \"COMMISSAIRE\" }" },
            "url": { "raw": "{{auth_base}}/auth/register", "host": ["{{auth_base}}"], "path": ["auth","register"] }
          },
          "event": [{ "listen": "test", "script": { "exec": ["pm.test(\"Status code is 201 or 200\", function () { pm.expect(pm.response.code).to.be.oneOf([200, 201]); });"], "type": "text/javascript" } }]
        },
        {
          "name": "Login - commissaire",
          "request": {
            "method": "POST",
            "header": [{ "key": "Content-Type", "value": "application/json" }],
            "body": { "mode": "raw", "raw": "{ \"username\": \"commissaire1\", \"password\": \"commiss123\" }" },
            "url": { "raw": "{{auth_base}}/auth/login", "host": ["{{auth_base}}"], "path": ["auth","login"] }
          },
          "event": [{ "listen": "test", "script": { "exec": [
            "pm.test(\"Status code is 200\", function () { pm.response.to.have.status(200); });",
            "try { var json = pm.response.json(); if (json && json.token) { pm.environment.set('token', json.token); pm.environment.set('jwt', 'Bearer ' + json.token); } } catch(e) {}"
          ], "type": "text/javascript" } }]
        },
        {
          "name": "Me",
          "request": {
            "method": "GET",
            "header": [{ "key": "Authorization", "value": "{{jwt}}" }],
            "url": { "raw": "{{auth_base}}/auth/me", "host": ["{{auth_base}}"], "path": ["auth","me"] }
          },
          "event": [{ "listen": "test", "script": { "exec": [
            "pm.test(\"Status 200\", function(){ pm.response.to.have.status(200); });",
            "try { var json = pm.response.json(); pm.test('has username/email', function(){ pm.expect(json).to.have.property('username'); pm.expect(json).to.have.property('email'); }); } catch(e) {}"
          ], "type": "text/javascript" } }]
        }
      ]
    },
    {
      "name": "participants-service",
      "item": [
        {
          "name": "Athlete - Create Profile",
          "request": {
            "method": "POST",
            "header": [{ "key": "Authorization", "value": "{{jwt}}" }, { "key": "Content-Type", "value": "application/json" }],
            "url": { "raw": "{{participants_base}}/api/athlete", "host": ["{{participants_base}}"], "path": ["api","athlete"] }
          },
          "event": [{ "listen": "test", "script": { "exec": [
            "pm.test(\"Status 201 or 200\", function(){ pm.expect(pm.response.code).to.be.oneOf([200,201]); });",
            "try { var json = pm.response.json(); if (json && json.id) { pm.environment.set('athlete_id', json.id); } } catch(e) {}"
          ], "type": "text/javascript" } }]
        },
        {
          "name": "Athlete - Post Info (upsert)",
          "request": {
            "method": "POST",
            "header": [{ "key": "Content-Type", "value": "application/json" }, { "key": "Authorization", "value": "{{jwt}}" }],
            "body": { "mode": "raw", "raw": "{ \"nom\": \"Dupont\", \"prenom\": \"Marie\", \"dateNaissance\": \"2000-03-22\", \"pays\": \"Belgique\" }" },
            "url": { "raw": "{{participants_base}}/api/athlete/{{athlete_id}}/info", "host": ["{{participants_base}}"], "path": ["api","athlete","{{athlete_id}}","info"] }
          },
          "event": [{ "listen": "test", "script": { "exec": ["pm.test(\"Status 200 or 201\", function(){ pm.expect(pm.response.code).to.be.oneOf([200,201]); });"], "type": "text/javascript" } }]
        },
        {
          "name": "Athlete - Post Doc",
          "request": {
            "method": "POST",
            "header": [{ "key": "Content-Type", "value": "application/json" }, { "key": "Authorization", "value": "{{jwt}}" }],
            "body": { "mode": "raw", "raw": "{ \"docs\": { \"certificatMedical\": \"certificat_medical_dupont.pdf\", \"passport\": \"passport_dupont.pdf\" } }" },
            "url": { "raw": "{{participants_base}}/api/athlete/{{athlete_id}}/doc", "host": ["{{participants_base}}"], "path": ["api","athlete","{{athlete_id}}","doc"] }
          },
          "event": [{ "listen": "test", "script": { "exec": ["pm.test(\"Status 200\", function(){ pm.response.to.have.status(200); });"], "type": "text/javascript" } }]
        },
        {
          "name": "Athlete - Post Remarque",
          "request": {
            "method": "POST",
            "header": [{ "key": "Content-Type", "value": "application/json" }, { "key": "Authorization", "value": "{{jwt}}" }],
            "body": { "mode": "raw", "raw": "{ \"observation\": \"Certificat médical valide\" }" },
            "url": { "raw": "{{participants_base}}/api/athlete/{{athlete_id}}/remarque", "host": ["{{participants_base}}"], "path": ["api","athlete","{{athlete_id}}","remarque"] }
          },
          "event": [{ "listen": "test", "script": { "exec": ["pm.test(\"Status 200\", function(){ pm.response.to.have.status(200); });"], "type": "text/javascript" } }]
        },
        {
          "name": "Commissaire - List Athletes",
          "request": {
            "method": "GET",
            "header": [{ "key": "Authorization", "value": "{{jwt}}" }],
            "url": { "raw": "{{participants_base}}/api/commissaire/athletes", "host": ["{{participants_base}}"], "path": ["api","commissaire","athletes"] }
          },
          "event": [{ "listen": "test", "script": { "exec": ["pm.test(\"Status 200\", function(){ pm.response.to.have.status(200); });"], "type": "text/javascript" } }]
        },
        {
          "name": "Commissaire - Get Athlete Info",
          "request": {
            "method": "GET",
            "header": [{ "key": "Authorization", "value": "{{jwt}}" }],
            "url": { "raw": "{{participants_base}}/api/commissaire/athletes/{{athlete_id}}/info", "host": ["{{participants_base}}"], "path": ["api","commissaire","athletes","{{athlete_id}}","info"] }
          },
          "event": [{ "listen": "test", "script": { "exec": ["pm.test(\"Status 200\", function(){ pm.response.to.have.status(200); });"], "type": "text/javascript" } }]
        },
        {
          "name": "Commissaire - Get Athlete Docs",
          "request": {
            "method": "GET",
            "header": [{ "key": "Authorization", "value": "{{jwt}}" }],
            "url": { "raw": "{{participants_base}}/api/commissaire/athletes/{{athlete_id}}/doc", "host": ["{{participants_base}}"], "path": ["api","commissaire","athletes","{{athlete_id}}","doc"] }
          },
          "event": [{ "listen": "test", "script": { "exec": ["pm.test(\"Status 200\", function(){ pm.response.to.have.status(200); });"], "type": "text/javascript" } }]
        },
        {
          "name": "Commissaire - Post Validation",
          "request": {
            "method": "POST",
            "header": [{ "key": "Content-Type", "value": "application/json" }, { "key": "Authorization", "value": "{{jwt}}" }],
            "body": { "mode": "raw", "raw": "{ \"valide\": true }" },
            "url": { "raw": "{{participants_base}}/api/commissaire/athletes/{{athlete_id}}/validation", "host": ["{{participants_base}}"], "path": ["api","commissaire","athletes","{{athlete_id}}","validation"] }
          },
          "event": [{ "listen": "test", "script": { "exec": ["pm.test(\"Status 200\", function(){ pm.response.to.have.status(200); });"], "type": "text/javascript" } }]
        }
      ]
    },
    {
      "name": "incident-service",
      "item": [
        {
          "name": "Create Incident",
          "request": {
            "method": "POST",
            "header": [{ "key": "Content-Type", "value": "application/json" }, { "key": "Authorization", "value": "{{jwt}}" }],
            "body": { "mode": "raw", "raw": "{ \"description\": \"Incident test\", \"status\": \"ACTIF\", \"type\": \"TECHNIQUE\", \"impactLevel\": \"MOYEN\", \"location\": \"Lieu\", \"reportedBy\": \"user1\" }" },
            "url": { "raw": "{{incident_base}}/api/incidents", "host": ["{{incident_base}}"], "path": ["api","incidents"] }
          },
          "event": [{ "listen": "test", "script": { "exec": [
            "pm.test(\"Status 201\", function(){ pm.response.to.have.status(201); });",
            "try { var json = pm.response.json(); if (json && json.id) { pm.environment.set('incident_id', json.id); } } catch(e) {}"
          ], "type": "text/javascript" } }]
        },
        {
          "name": "Get Incident by Id",
          "request": { "method": "GET", "header": [{ "key": "Authorization", "value": "{{jwt}}" }], "url": { "raw": "{{incident_base}}/api/incidents/{{incident_id}}", "host": ["{{incident_base}}"], "path": ["api","incidents","{{incident_id}}"] } }
        }
      ]
    },
    {
      "name": "event-service",
      "item": [
        {
          "name": "Lieux - Create",
          "request": {
            "method": "POST",
            "header": [{ "key": "Content-Type", "value": "application/json" }, { "key": "Authorization", "value": "{{jwt}}" }],
            "body": { "mode": "raw", "raw": "{ \"nom\": \"Stade Olympique\", \"ville\": \"Paris\", \"adresse\": \"1 Rue Olympique\", \"capacite\": 80000 }" },
            "url": { "raw": "{{event_base}}/lieux", "host": ["{{event_base}}"], "path": ["lieux"] }
          },
          "event": [{ "listen": "test", "script": { "exec": [
            "pm.test(\"Status 201\", function(){ pm.response.to.have.status(201); });",
            "try { var json = pm.response.json(); if (json && json.id) { pm.environment.set('lieu_id', json.id); } } catch(e) {}"
          ], "type": "text/javascript" } }]
        },
        {
          "name": "Events - Create",
          "request": {
            "method": "POST",
            "header": [{ "key": "Content-Type", "value": "application/json" }, { "key": "Authorization", "value": "{{jwt}}" }],
            "body": { "mode": "raw", "raw": "{ \"name\": \"Championnat National d'Athlétisme\", \"date\": \"2025-06-15T10:00:00Z\", \"lieuId\": \"{{lieu_id}}\", \"description\": \"Championnat 2025\" }" },
            "url": { "raw": "{{event_base}}/events", "host": ["{{event_base}}"], "path": ["events"] }
          },
          "event": [{ "listen": "test", "script": { "exec": [
            "pm.test(\"Status 201\", function(){ pm.response.to.have.status(201); });",
            "try { var json = pm.response.json(); if (json && json.id) { pm.environment.set('event_id', json.id); } } catch(e) {}"
          ], "type": "text/javascript" } }]
        },
        {
          "name": "Epreuves - Create",
          "request": {
            "method": "POST",
            "header": [{ "key": "Content-Type", "value": "application/json" }, { "key": "Authorization", "value": "{{jwt}}" }],
            "body": { "mode": "raw", "raw": "{ \"nom\": \"Finale 100m\" }" },
            "url": { "raw": "{{event_base}}/epreuves", "host": ["{{event_base}}"], "path": ["epreuves"] }
          },
          "event": [{ "listen": "test", "script": { "exec": [
            "pm.test(\"Status 201\", function(){ pm.response.to.have.status(201); });",
            "try { var json = pm.response.json(); if (json && json.id) { pm.environment.set('epreuve_id', json.id); } } catch(e) {}"
          ], "type": "text/javascript" } }]
        },
        {
          "name": "Epreuves - Add Athlete",
          "request": {
            "method": "POST",
            "header": [{ "key": "Content-Type", "value": "application/json" }, { "key": "Authorization", "value": "{{jwt}}" }],
            "body": { "mode": "raw", "raw": "{ \"athleteId\": {{athlete_id}} }" },
            "url": { "raw": "{{event_base}}/epreuves/{{epreuve_id}}/athletes", "host": ["{{event_base}}"], "path": ["epreuves","{{epreuve_id}}","athletes"] }
          },
          "event": [
            {
              "listen": "test",
              "script": {
                "exec": [
                  "pm.test(\"Status 200\", function(){ pm.response.to.have.status(200); });",
                  "try {",
                  "  var json = pm.response.json();",
                  "  pm.test('Has athleteIds array', function(){ pm.expect(json).to.have.property('athleteIds'); pm.expect(Array.isArray(json.athleteIds)).to.be.true; });",
                  "  var aid = String(pm.environment.get('athlete_id'));",
                  "  var present = Array.isArray(json.athleteIds) && json.athleteIds.some(function(id){ return String(id) === aid; });",
                  "  pm.test('athleteIds contains athlete_id', function(){ pm.expect(present).to.be.true; });",
                  "  pm.environment.set('epreuve_participants_count', json.athleteIds.length);",
                  "  pm.environment.set('expect_athlete_participating', 'true');",
                  "} catch(e) {}"
                ],
                "type": "text/javascript"
              }
            }
          ]
        },
        {
          "name": "Epreuves - Add Athlete (no auth -> 401)",
          "request": {
            "method": "POST",
            "header": [
              { "key": "Content-Type", "value": "application/json" }
            ],
            "body": { "mode": "raw", "raw": "{ \"athleteId\": 2 }" },
            "url": { "raw": "{{event_base}}/epreuves/{{epreuve_id}}/athletes", "host": ["{{event_base}}"], "path": ["epreuves","{{epreuve_id}}","athletes"] }
          },
          "event": [
            {
              "listen": "test",
              "script": {
                "exec": [
                  "pm.test('Status is 401', function(){ pm.response.to.have.status(401); });",
                  "try { var json = pm.response.json(); pm.test('Has message', function(){ pm.expect(json.message || '').to.not.be.empty; }); } catch(e) {}"
                ],
                "type": "text/javascript"
              }
            }
          ]
        },
        {
          "name": "Epreuves - Add Athletes (bulk)",
          "request": {
            "method": "POST",
            "header": [{ "key": "Content-Type", "value": "application/json" }, { "key": "Authorization", "value": "{{jwt}}" }],
            "body": { "mode": "raw", "raw": "{ \"athleteIds\": [ {{athlete_id}}, 2 ] }" },
            "url": { "raw": "{{event_base}}/epreuves/{{epreuve_id}}/athletes/bulk", "host": ["{{event_base}}"], "path": ["epreuves","{{epreuve_id}}","athletes","bulk"] }
          },
          "event": [
            {
              "listen": "test",
              "script": {
                "exec": [
                  "pm.test(\"Status 200\", function(){ pm.response.to.have.status(200); });",
                  "try {",
                  "  var json = pm.response.json();",
                  "  pm.test('Has athleteIds array', function(){ pm.expect(json).to.have.property('athleteIds'); pm.expect(Array.isArray(json.athleteIds)).to.be.true; });",
                  "  var aid = String(pm.environment.get('athlete_id'));",
                  "  var hasAid = json.athleteIds.some(function(id){ return String(id) === aid; });",
                  "  var has2 = json.athleteIds.some(function(id){ return String(id) === '2'; });",
                  "  pm.test('contains both ids', function(){ pm.expect(hasAid && has2).to.be.true; });",
                  "  pm.environment.set('epreuve_participants_count', json.athleteIds.length);",
                  "} catch(e) {}"
                ],
                "type": "text/javascript"
              }
            }
          ]
        },
        {
          "name": "Epreuves - Get Participants",
          "request": {
            "method": "GET",
            "header": [{ "key": "Authorization", "value": "{{jwt}}" }],
            "url": { "raw": "{{event_base}}/epreuves/{{epreuve_id}}/athletes", "host": ["{{event_base}}"], "path": ["epreuves","{{epreuve_id}}","athletes"] }
          },
          "event": [
            {
              "listen": "test",
              "script": {
                "exec": [
                  "pm.test(\"Status 200\", function(){ pm.response.to.have.status(200); });",
                  "try {",
                  "  var json = pm.response.json();",
                  "  var arr = Array.isArray(json) ? json : (Array.isArray(json && json.athleteIds) ? json.athleteIds : (json ? Object.values(json) : []));",
                  "  var aid = String(pm.environment.get('athlete_id'));",
                  "  var present = arr.some(function(id){ return String(id) === aid || (id && id.id && String(id.id) === aid); });",
                  "  pm.test('contains athlete_id', function(){ pm.expect(present).to.be.true; });",
                  "  pm.environment.set('epreuve_participants_count', arr.length || (json && json.athleteIds && json.athleteIds.length) || 0);",
                  "} catch(e) {}"
                ],
                "type": "text/javascript"
              }
            }
          ]
        },
        {
          "name": "Epreuves - Check Athlete Participation",
          "request": {
            "method": "GET",
            "header": [
              { "key": "Authorization", "value": "{{jwt}}" }
            ],
            "url": {
              "raw": "{{event_base}}/epreuves/{{epreuve_id}}/athletes/{{athlete_id}}",
              "host": ["{{event_base}}"],
              "path": ["epreuves","{{epreuve_id}}","athletes","{{athlete_id}}"]
            }
          },
          "event": [
            {
              "listen": "test",
              "script": {
                "exec": [
                  "pm.test(\"Status is 200\", function(){ pm.response.to.have.status(200); });",
                  "try {",
                  "  var json = pm.response.json();",
                  "  pm.test('Has participating boolean', function(){ pm.expect(json).to.have.property('participating'); pm.expect(json.participating).to.be.a('boolean'); });",
                  "  var expectParticipating = pm.environment.get('expect_athlete_participating');",
                  "  if (expectParticipating === 'true') { pm.test('participating is true', function(){ pm.expect(json.participating).to.be.true; }); }",
                  "  pm.environment.set('epreuve_participating', json.participating);",
                  "} catch(e) {}"
                ],
                "type": "text/javascript"
              }
            }
          ]
        },
        {
          "name": "Epreuves - Add Athlete (missing athleteId -> 400)",
          "request": {
            "method": "POST",
            "header": [
              { "key": "Content-Type", "value": "application/json" },
              { "key": "Authorization", "value": "{{jwt}}" }
            ],
            "body": { "mode": "raw", "raw": "{}" },
            "url": { "raw": "{{event_base}}/epreuves/{{epreuve_id}}/athletes", "host": ["{{event_base}}"], "path": ["epreuves","{{epreuve_id}}","athletes"] }
          },
          "event": [
            {
              "listen": "test",
              "script": {
                "exec": [
                  "pm.test('Status 400', function(){ pm.response.to.have.status(400); });",
                  "try { var json = pm.response.json(); pm.test('Has message mentioning athleteId', function(){ pm.expect(json.message || '').to.include('athleteId'); }); } catch(e) {}"
                ],
                "type": "text/javascript"
              }
            }
          ]
        },
        {
          "name": "Epreuves - Add Athlete (epreuve not found -> 404)",
          "request": {
            "method": "POST",
            "header": [
              { "key": "Content-Type", "value": "application/json" },
              { "key": "Authorization", "value": "{{jwt}}" }
            ],
            "body": { "mode": "raw", "raw": "{ \"athleteId\": {{athlete_id}} }" },
            "url": { "raw": "{{event_base}}/epreuves/999999/athletes", "host": ["{{event_base}}"], "path": ["epreuves","999999","athletes"] }
          },
          "event": [
            {
              "listen": "test",
              "script": {
                "exec": [
                  "pm.test('Status 404', function(){ pm.response.to.have.status(404); });",
                  "try { var json = pm.response.json(); pm.test('Has message Epreuve not found', function(){ pm.expect(json.message || '').to.include('Epreuve not found'); }); } catch(e) {}"
                ],
                "type": "text/javascript"
              }
            }
          ]
        },
        {
          "name": "Epreuves - Get Participants (epreuve not found -> 404)",
          "request": {
            "method": "GET",
            "header": [{ "key": "Authorization", "value": "{{jwt}}" }],
            "url": { "raw": "{{event_base}}/epreuves/999999/athletes", "host": ["{{event_base}}"], "path": ["epreuves","999999","athletes"] }
          },
          "event": [
            {
              "listen": "test",
              "script": {
                "exec": [
                  "pm.test('Status 404', function(){ pm.response.to.have.status(404); });",
                  "try { var json = pm.response.json(); pm.test('Has message Epreuve not found', function(){ pm.expect(json.message || '').to.include('Epreuve not found'); }); } catch(e) {}"
                ],
                "type": "text/javascript"
              }
            }
          ]
        },
        {
          "name": "Epreuves - Check Athlete Participation (epreuve not found -> 404)",
          "request": {
            "method": "GET",
            "header": [{ "key": "Authorization", "value": "{{jwt}}" }],
            "url": { "raw": "{{event_base}}/epreuves/999999/athletes/{{athlete_id}}", "host": ["{{event_base}}"], "path": ["epreuves","999999","athletes","{{athlete_id}}"] }
          },
          "event": [
            {
              "listen": "test",
              "script": {
                "exec": [
                  "pm.test('Status 404', function(){ pm.response.to.have.status(404); });",
                  "try { var json = pm.response.json(); pm.test('Has message Epreuve not found', function(){ pm.expect(json.message || '').to.include('Epreuve not found'); }); } catch(e) {}"
                ],
                "type": "text/javascript"
              }
            }
          ]
        },
        {
          "name": "Competitions - Create",
          "request": {
            "method": "POST",
            "header": [{ "key": "Content-Type", "value": "application/json" }, { "key": "Authorization", "value": "{{jwt}}" }],
            "body": { "mode": "raw", "raw": "{ \"name\": \"100m Sprint Hommes\", \"type\": \"ATHLETICS\", \"category\": \"SENIOR\", \"eventId\": \"{{event_id}}\" }" },
            "url": { "raw": "{{event_base}}/competitions", "host": ["{{event_base}}"], "path": ["competitions"] }
          },
          "event": [{ "listen": "test", "script": { "exec": [
            "pm.test(\"Status 201\", function(){ pm.response.to.have.status(201); });",
            "try { var json = pm.response.json(); if (json && json.id) { pm.environment.set('competition_id', json.id); } } catch(e) {}"
          ], "type": "text/javascript" } }]
        },
        {
          "name": "Competitions - Add Epreuve (under competition)",
          "request": {
            "method": "POST",
            "header": [
              { "key": "Content-Type", "value": "application/json" },
              { "key": "Authorization", "value": "{{jwt}}" }
            ],
            "body": { "mode": "raw", "raw": "{ \"nom\": \"Finale 100m Sprint\", \"date\": \"2025-06-15\" }" },
            "url": { "raw": "{{event_base}}/competitions/{{competition_id}}/epreuves", "host": ["{{event_base}}"], "path": ["competitions","{{competition_id}}","epreuves"] }
          },
          "event": [
            {
              "listen": "test",
              "script": {
                "exec": [
                  "pm.test(\"Status 201\", function(){ pm.response.to.have.status(201); });",
                  "try {",
                  "  var json = pm.response.json();",
                  "  pm.test('Response has id', function(){ pm.expect(json).to.have.property('id'); });",
                  "  if (json && json.id) pm.environment.set('epreuve_id', json.id);",
                  "  var compResp = json.competitionId || (json.competition && json.competition.id);",
                  "  var compEnv = String(pm.environment.get('competition_id') || '');",
                  "  if (compEnv) pm.test('competitionId matches', function(){ pm.expect(String(compResp)).to.equal(compEnv); });",
                  "} catch(e) {}"
                ],
                "type": "text/javascript"
              }
            }
          ]
        },
        {
          "name": "Competitions - Attach Existing Epreuve",
          "request": {
            "method": "POST",
            "header": [ { "key": "Authorization", "value": "{{jwt}}" } ],
            "url": { "raw": "{{event_base}}/competitions/{{competition_id}}/epreuves/{{epreuve_id}}", "host": ["{{event_base}}"], "path": ["competitions","{{competition_id}}","epreuves","{{epreuve_id}}"] }
          },
          "event": [
            {
              "listen": "test",
              "script": {
                "exec": [
                  "pm.test('Status 200', function(){ pm.response.to.have.status(200); });",
                  "try {",
                  "  var json = pm.response.json();",
                  "  var compResp = json.competitionId || (json.competition && json.competition.id);",
                  "  pm.test('competitionId set', function(){ pm.expect(String(compResp)).to.equal(String(pm.environment.get('competition_id'))); });",
                  "} catch(e) {}"
                ],
                "type": "text/javascript"
              }
            }
          ]
        },
        {
          "name": "Competitions - List Epreuves",
          "request": {
            "method": "GET",
            "header": [ { "key": "Authorization", "value": "{{jwt}}" } ],
            "url": { "raw": "{{event_base}}/competitions/{{competition_id}}/epreuves", "host": ["{{event_base}}"], "path": ["competitions","{{competition_id}}","epreuves"] }
          },
          "event": [
            {
              "listen": "test",
              "script": {
                "exec": [
                  "pm.test('Status 200', function(){ pm.response.to.have.status(200); });",
                  "try {",
                  "  var json = pm.response.json();",
                  "  var eprId = String(pm.environment.get('epreuve_id') || '');",
                  "  var found = Array.isArray(json) && json.some(function(item){ return String(item.id) === eprId; });",
                  "  if (eprId) pm.test('contains epreuve_id', function(){ pm.expect(found).to.be.true; });",
                  "} catch(e) {}"
                ],
                "type": "text/javascript"
              }
            }
          ]
        }
      ]
    },
    {
      "name": "billetterie",
      "item": [
        {
          "name": "Create Ticket",
          "request": {
            "method": "POST",
            "header": [{ "key": "Content-Type", "value": "application/json" }, { "key": "Authorization", "value": "{{jwt}}" }],
            "body": { "mode": "raw", "raw": "{ \"spectatorId\": 1, \"eventId\": \"{{event_id}}\", \"seat\": \"A12\", \"category\": \"STANDARD\", \"price\": 25.00 }" },
            "url": { "raw": "{{billetterie_base}}/api/tickets", "host": ["{{billetterie_base}}"], "path": ["api","tickets"] }
          },
          "event": [{ "listen": "test", "script": { "exec": [
            "pm.test(\"Status 201\", function(){ pm.response.to.have.status(201); });",
            "try { var json = pm.response.json(); if (json && json.id) { pm.environment.set('ticket_id', json.id); } } catch(e) {}"
          ], "type": "text/javascript" } }]
        }
      ]
    },
    {
      "name": "abonnement-service",
      "item": [
        {
          "name": "S'abonner à une compétition",
          "request": {
            "method": "POST",
            "header": [{ "key": "Authorization", "value": "{{jwt}}" }],
            "url": { "raw": "{{abonnement_base}}/api/abonnements/subscribe?userId=1&competitionId={{competition_id}}", "host": ["{{abonnement_base}}"], "path": ["api","abonnements","subscribe"], "query": [ { "key": "userId", "value": "1" }, { "key": "competitionId", "value": "{{competition_id}}" } ] }
          },
          "event": [{ "listen": "test", "script": { "exec": ["pm.test(\"Status 200 or 201\", function(){ pm.expect(pm.response.code).to.be.oneOf([200,201]); });"], "type": "text/javascript" } }]
        }
      ]
    },
    {
      "name": "ciblorgasport (monolith)",
      "item": [
        {
          "name": "Auth - Login (monolith)",
          "request": {
            "method": "POST",
            "header": [{ "key": "Content-Type", "value": "application/json" }],
            "body": { "mode": "raw", "raw": "{ \"username\": \"testuser\", \"password\": \"Test123!\" }" },
            "url": { "raw": "{{api_base}}/api/auth/login", "host": ["{{api_base}}"], "path": ["api","auth","login"] }
          },
          "event": [{ "listen": "test", "script": { "exec": [
            "pm.test(\"Status 200\", function(){ pm.response.to.have.status(200); });",
            "try { var json = pm.response.json(); if (json && json.token) { pm.environment.set('token', json.token); pm.environment.set('jwt','Bearer '+json.token); } } catch(e) {}"
          ], "type": "text/javascript" } }]
        }
      ]
    }
  ]
}
